rss_generator/__init__.py
rss_generator/__main__.py
rss_generator/cli.py
rss_generator/common.py
rss_generator/feed.xsl
rss_generator/parsers.py
rss_generator/sites.py
rss_generator/standalone/__init__.py
rss_generator/standalone/diariodominho.py
rss_generator/standalone/immich_blog.py
rss_generator-0.3.0.dist-info/METADATA
rss_generator-0.3.0.dist-info/WHEEL
rss_generator-0.3.0.dist-info/entry_points.txt
rss_generator-0.3.0.dist-info/RECORD
