Metadata-Version: 2.4
Name: rss-generator
Version: 0.3.0
Summary: Modern CLI tool for generating RSS feeds from websites and uploading to MinIO
Project-URL: Homepage, https://github.com/pedromcaraujo/rss-generator
Project-URL: Repository, https://github.com/pedromcaraujo/rss-generator
Project-URL: Issues, https://github.com/pedromcaraujo/rss-generator/issues
Author-email: Pedro Araujo <pedromcaraujo@users.noreply.github.com>
License: MIT
Keywords: cli,feed,generator,minio,rss,s3
Classifier: Development Status :: 4 - Beta
Classifier: Intended Audience :: Developers
Classifier: License :: OSI Approved :: MIT License
Classifier: Programming Language :: Python :: 3
Classifier: Programming Language :: Python :: 3.12
Classifier: Programming Language :: Python :: 3.13
Requires-Python: >=3.12
Requires-Dist: beautifulsoup4>=4.14.2
Requires-Dist: boto3>=1.40.43
Requires-Dist: feedgen>=1.0.0
Requires-Dist: jinja2>=3.1.0
Requires-Dist: playwright>=1.55.0
Requires-Dist: python-dotenv>=1.1.1
Requires-Dist: requests>=2.32.5
Requires-Dist: rich>=14.1.0
Requires-Dist: typer>=0.19.2
